fx/Xchanger.py
fx/__init__.py
fx/erros.py
Xchanger-0.1.1.dist-info/LICENSE.txt
Xchanger-0.1.1.dist-info/METADATA
Xchanger-0.1.1.dist-info/WHEEL
Xchanger-0.1.1.dist-info/top_level.txt
Xchanger-0.1.1.dist-info/RECORD
